realtime/__init__.py
realtime/__main__.py
realtime/_realtime_function.py
realtime/app.py
realtime/cli.py
realtime/data.py
realtime/ops/combine_latest.py
realtime/ops/join.py
realtime/ops/map.py
realtime/ops/merge.py
realtime/ops/unzip_array.py
realtime/plugins/VAD/silero_model.py
realtime/plugins/__init__.py
realtime/plugins/audio_convertor.py
realtime/plugins/azure_tts.py
realtime/plugins/base_plugin.py
realtime/plugins/cartesia_tts.py
realtime/plugins/deepgram_stt.py
realtime/plugins/eleven_labs_tts.py
realtime/plugins/fal_vision.py
realtime/plugins/fireworks_llm.py
realtime/plugins/fireworks_vision.py
realtime/plugins/gemini_vision.py
realtime/plugins/groq_llm.py
realtime/plugins/key_frame_detector.py
realtime/plugins/lip_sync.py
realtime/plugins/openai_assistant.py
realtime/plugins/openai_llm.py
realtime/plugins/openai_vision.py
realtime/plugins/silero_vad.py
realtime/plugins/token_aggregator.py
realtime/plugins/vision_plugin.py
realtime/plugins/whisper_stt.py
realtime/server.py
realtime/streaming_endpoint/AudioRTCDriver.py
realtime/streaming_endpoint/TextRTCDriver.py
realtime/streaming_endpoint/VideoRTCDriver.py
realtime/streaming_endpoint/__init__.py
realtime/streaming_endpoint/server.py
realtime/streams.py
realtime/types/audio.py
realtime/utils/__init__.py
realtime/utils/audio.py
realtime/utils/clock.py
realtime/utils/cloneable_queue.py
realtime/utils/constants.py
realtime/utils/images.py
realtime/utils/tracing.py
realtime/utils/vad.py
realtime/web_endpoint/__init__.py
realtime/websocket/__init__.py
realtime/websocket/handler.py
realtime/websocket/processors.py
realtime_client-0.1.146.dist-info/LICENSE.txt
realtime_client-0.1.146.dist-info/METADATA
realtime_client-0.1.146.dist-info/WHEEL
realtime_client-0.1.146.dist-info/entry_points.txt
realtime_client-0.1.146.dist-info/RECORD
