Metadata-Version: 2.1
Name: realtime-client
Version: 0.1.146
Summary: 
Author: Adapt
Author-email: hello@getadapt.ai
Requires-Python: >=3.9,<3.12
Classifier: Programming Language :: Python :: 3
Classifier: Programming Language :: Python :: 3.9
Classifier: Programming Language :: Python :: 3.10
Classifier: Programming Language :: Python :: 3.11
Provides-Extra: plugins
Requires-Dist: aiohttp (>=3.9.5,<4.0.0)
Requires-Dist: aiortc (>=1.8.0,<2.0.0)
Requires-Dist: azure-cognitiveservices-speech (>=1.37.0,<2.0.0)
Requires-Dist: click (>=8.1.7,<9.0.0)
Requires-Dist: dill (>=0.3.8,<0.4.0)
Requires-Dist: elevenlabs (>=1.2.0,<2.0.0) ; extra == "plugins"
Requires-Dist: fal-client (>=0.4.0,<0.5.0) ; extra == "plugins"
Requires-Dist: fastapi (>=0.110.2,<0.111.0)
Requires-Dist: fireworks-ai (>=0.14.0,<0.15.0) ; extra == "plugins"
Requires-Dist: google-cloud-vision (>=3.7.2,<4.0.0) ; extra == "plugins"
Requires-Dist: google-generativeai (>=0.5.3,<0.6.0) ; extra == "plugins"
Requires-Dist: numpy (>=1.26.4,<2.0.0)
Requires-Dist: openai (>=1.35.10,<2.0.0)
Requires-Dist: opencv-python-headless (>=4.10.0.82,<5.0.0.0) ; extra == "plugins"
Requires-Dist: pillow (>=10.3.0,<11.0.0)
Requires-Dist: pydub (>=0.25.1,<0.26.0)
Requires-Dist: pyloudnorm (>=0.1.1,<0.2.0)
Requires-Dist: python-multipart (>=0.0.9,<0.0.10)
Requires-Dist: realtime-aioice (>=0.9.0,<0.10.0)
Requires-Dist: requests (>=2.31.0,<3.0.0)
Requires-Dist: scipy (>=1.13.1,<2.0.0)
Requires-Dist: sentry-sdk (>=2.9.0,<3.0.0)
Requires-Dist: setuptools (>=69.5.1,<70.0.0)
Requires-Dist: silero-vad (>=5.1,<6.0)
Requires-Dist: torch (==2.3.0+cpu) ; sys_platform == "linux"
Requires-Dist: torch (==2.3.0+cpu) ; sys_platform == "win32"
Requires-Dist: torch (>=2.3.0,<3.0.0) ; sys_platform == "darwin"
Requires-Dist: torchaudio (==2.3.0+cpu) ; sys_platform == "linux"
Requires-Dist: torchaudio (==2.3.0+cpu) ; sys_platform == "win32"
Requires-Dist: torchaudio (>=2.3.0,<3.0.0) ; sys_platform == "darwin"
Requires-Dist: torchvision (==0.18.0+cpu) ; sys_platform == "linux"
Requires-Dist: torchvision (==0.18.0+cpu) ; sys_platform == "win32"
Requires-Dist: torchvision (>=0.18.0,<0.19.0) ; sys_platform == "darwin"
Requires-Dist: urllib3 (<2.0)
Requires-Dist: uvicorn (>=0.29.0,<0.30.0)
Requires-Dist: websockets (>=12.0,<13.0)
